{
  "meta": {
    "version": "v1.0-phase5",
    "phase": "Phase 5 — Canon Lock (Business Decisions)",
    "description": "Business-critical decision set for AtlasForge’s canon, structure, subsidiaries, product narrative, and public positioning.",
    "canon_doc_path": "docs/atlasforge_canon_index.md"
  },

  "blocks": [

    {
      "id": "core_pillars",
      "title": "Core Pillars — Public Canon Priority",
      "description": "Decide how prominently each AtlasForge pillar should appear in public content and brand canon.",
      "items": [

        {
          "id": "pillar_atlasforge_games",
          "label": "How prominently should AtlasForge Games appear across the website and canon?",
          "type": "select",
          "options": [
            { "value": "A_HERO", "label": "A — Top-tier hero presence (featured on homepage + navigation)" },
            { "value": "B_MAJOR", "label": "B — Major section presence (prominent but secondary)" },
            { "value": "C_MINOR", "label": "C — Minor section only (footer card or secondary link)" },
            { "value": "D_BACKGROUND", "label": "D — Background mention only (no surface placement)" },
            { "value": "E_HIDDEN", "label": "E — Internal only (not shown publicly)" }
          ],
          "default": "B_MAJOR"
        },

        {
          "id": "pillar_atlasstudio",
          "label": "How prominently should AtlasStudio (tools/workstation) appear?",
          "type": "select",
          "options": [
            { "value": "A_HERO", "label": "A — Hero / showcased toolset" },
            { "value": "B_MAJOR", "label": "B — Major section with CTA" },
            { "value": "C_MINOR", "label": "C — Brief mention only" },
            { "value": "D_BACKGROUND", "label": "D — Background-only explanation" },
            { "value": "E_HIDDEN", "label": "E — Not shown publicly" }
          ],
          "default": "B_MAJOR"
        },

        {
          "id": "pillar_atlasv",
          "label": "How central should the Atlas-V Engine identity be?",
          "type": "select",
          "options": [
            { "value": "A_HERO", "label": "A — Central brain of the company (front-and-center)" },
            { "value": "B_MAJOR", "label": "B — Major feature section" },
            { "value": "C_MINOR", "label": "C — Secondary feature mention" },
            { "value": "D_BACKGROUND", "label": "D — Internal role explained quietly" },
            { "value": "E_HIDDEN", "label": "E — Internal-only tool" }
          ],
          "default": "A_HERO"
        }

      ]
    },

    {
      "id": "subsidiary_expansion",
      "title": "Subsidiaries & Additional Lines — Approve/Deny",
      "description": "Decide whether each proposed subsidiary or product-line extension should become canon.",
      "items": [

        {
          "id": "approve_merchforge",
          "label": "Should MerchForge (AtlasForge merch line) be canon?",
          "type": "select",
          "options": [
            { "value": "APPROVE", "label": "Approve" },
            { "value": "DENY", "label": "Deny" }
          ],
          "default": "APPROVE"
        },

        {
          "id": "approve_templatefactory",
          "label": "Should TemplateFactory (game/tool templates) be canon?",
          "type": "select",
          "options": [
            { "value": "APPROVE", "label": "Approve" },
            { "value": "DENY", "label": "Deny" }
          ],
          "default": "APPROVE"
        },

        {
          "id": "approve_hypercasualforge",
          "label": "Should Hypercasual Forge be an official game label?",
          "type": "select",
          "options": [
            { "value": "APPROVE", "label": "Approve" },
            { "value": "DENY", "label": "Deny" }
          ],
          "default": "APPROVE"
        }
      ]
    },

    {
      "id": "brand_roles",
      "title": "Brand Positioning & Roles",
      "description": "Set clarity on what each brand exists to do and how it is framed.",
      "items": [

        {
          "id": "brand_games_role",
          "label": "What role should AtlasForge Games play?",
          "type": "select",
          "options": [
            { "value": "A_FLAGSHIP", "label": "A — Flagship product identity" },
            { "value": "B_MAJOR", "label": "B — Major creative line" },
            { "value": "C_SUPPORT", "label": "C — Support identity only" },
            { "value": "D_BACKGROUND", "label": "D — Background role" }
          ],
          "default": "A_FLAGSHIP"
        },

        {
          "id": "brand_media_role",
          "label": "Should AtlasForge Media (documentaries, storytelling, content) be formalized?",
          "type": "select",
          "options": [
            { "value": "YES", "label": "Yes" },
            { "value": "NO", "label": "No" }
          ],
          "default": "YES"
        }

      ]
    },

    {
      "id": "governance",
      "title": "Governance & Public Boundaries",
      "description": "Clarify what is disclosed publicly and what stays internal.",
      "items": [

        {
          "id": "governance_visibility",
          "label": "How transparent should governance and process documentation be?",
          "type": "select",
          "options": [
            { "value": "A_FULL", "label": "A — Fully transparent (public governance documents)" },
            { "value": "B_PARTIAL", "label": "B — Partial (high-level only)" },
            { "value": "C_MINIMAL", "label": "C — Minimal (rare disclosures)" },
            { "value": "D_HIDDEN", "label": "D — None (fully internal)" }
          ],
          "default": "B_PARTIAL"
        }

      ]
    }

  ]
}
